tictot/__init__.py
tictot/app.py
tictot/cli.py
tictot/commands/__init__.py
tictot/commands/export.py
tictot/config/__init__.py
tictot/config/config.py
tictot/db/__init__.py
tictot/db/crud.py
tictot/db/db.py
tictot/db/models.py
tictot/status/__init__.py
tictot/status/status.py
tictot/style.css
tictot/widgets/__init__.py
tictot/widgets/entries.py
tictot/widgets/timer.py
tictot-0.1.6.dist-info/METADATA
tictot-0.1.6.dist-info/WHEEL
tictot-0.1.6.dist-info/entry_points.txt
tictot-0.1.6.dist-info/RECORD
