Metadata-Version: 2.1
Name: tictot
Version: 0.1.6
Summary: A time tracker for the terminal made with textual.
Home-page: https://github.com/daniarlert/tictot
License: MIT
Keywords: cli,terminal,textual,time management
Author: daniarlert
Author-email: arlertdaniel@gmail.com
Requires-Python: >=3.11,<4.0
Classifier: License :: OSI Approved :: MIT License
Classifier: Programming Language :: Python :: 3
Classifier: Programming Language :: Python :: 3.11
Requires-Dist: click (>=8.1.3,<9.0.0)
Requires-Dist: sqlalchemy (>=2.0.4,<3.0.0)
Requires-Dist: textual[dev] (>=0.12.1,<0.13.0)
Project-URL: Repository, https://github.com/daniarlert/tictot
